ultrafastFitFunctions/__init__.py
ultrafastFitFunctions/backgrounds.py
ultrafastFitFunctions/dynamics.py
ultrafastFitFunctions/miscellaneous.py
ultrafastFitFunctions-0.3.0.dist-info/METADATA
ultrafastFitFunctions-0.3.0.dist-info/WHEEL
ultrafastFitFunctions-0.3.0.dist-info/top_level.txt
ultrafastFitFunctions-0.3.0.dist-info/RECORD
