Metadata-Version: 2.1
Name: ultrafastFitFunctions
Version: 0.3.0
Summary: Collection of common fit functions for discribing ultrafast and static physics phenomena
Home-page: https://github.com/EmCeBeh/ultrafastFitFunctions
Author: Martin Borchert
Author-email: martin.b@robothek.de
License: UNKNOWN
Platform: UNKNOWN
Requires-Dist: numpy
Requires-Dist: scipy
Requires-Dist: uncertainties
